keycache/__init__.py
keycache/blobstore.py
keycache/keycache.py
keycache/util.py
keycache-0.27.0.dist-info/LICENSE
keycache-0.27.0.dist-info/METADATA
keycache-0.27.0.dist-info/WHEEL
keycache-0.27.0.dist-info/top_level.txt
keycache-0.27.0.dist-info/RECORD
