Metadata-Version: 2.1
Name: keycache
Version: 0.27.0
Summary: Keycache is an AES encrypted keyvalue store for sensitive credentials.
Home-page: https://github.com/psytron/keycache
Author: Mico Malecki
Author-email: m@psytron.com
License: Apache 2.0
Platform: UNKNOWN
Requires-Dist: pyAesCrypt
Requires-Dist: cryptography
Requires-Dist: pyyaml
